digsandpaper/__init__.py
digsandpaper/default_config.json
digsandpaper/engine.py
digsandpaper/main.py
digsandpaper/sandpaper_utils.py
digsandpaper/search_server.py
digsandpaper/coarse/__init__.py
digsandpaper/coarse/coarse_component.py
digsandpaper/coarse/coarse_engine.py
digsandpaper/coarse/execute/__init__.py
digsandpaper/coarse/execute/execute_component_factory.py
digsandpaper/coarse/execute/execute_query_component.py
digsandpaper/coarse/execute/executor.py
digsandpaper/coarse/generate/__init__.py
digsandpaper/coarse/generate/field_weight_component.py
digsandpaper/coarse/generate/generate_component_factory.py
digsandpaper/coarse/generate/generator.py
digsandpaper/coarse/generate/query_compiler_component.py
digsandpaper/coarse/generate/type_doc_type_mapping_component.py
digsandpaper/coarse/generate/type_field_mapping_component.py
digsandpaper/coarse/generate/type_index_mapping_component.py
digsandpaper/coarse/generate/type_query_mapping_component.py
digsandpaper/coarse/generate/zone_field_mapping_component.py
digsandpaper/coarse/parameterize/__init__.py
digsandpaper/coarse/parameterize/clause_combination_component.py
digsandpaper/coarse/parameterize/extractor_hierarchy_component.py
digsandpaper/coarse/parameterize/field_combination_component.py
digsandpaper/coarse/parameterize/parameterize_component_factory.py
digsandpaper/coarse/parameterize/parameterizer.py
digsandpaper/coarse/parameterize/zone_hierarchy_component.py
digsandpaper/coarse/postprocess/__init__.py
digsandpaper/coarse/postprocess/postprocess_component_factory.py
digsandpaper/coarse/postprocess/postprocessor.py
digsandpaper/coarse/postprocess/similarity_score_rerank_component.py
digsandpaper/coarse/preprocess/__init__.py
digsandpaper/coarse/preprocess/clause_id_factory.py
digsandpaper/coarse/preprocess/constraint_consistency_factory.py
digsandpaper/coarse/preprocess/constraint_expansion_factory.py
digsandpaper/coarse/preprocess/constraint_relaxation_factory.py
digsandpaper-0.4.3.dist-info/METADATA
digsandpaper-0.4.3.dist-info/RECORD
digsandpaper-0.4.3.dist-info/WHEEL
digsandpaper-0.4.3.dist-info/top_level.txt
