Metadata-Version: 2.1
Name: digsandpaper
Version: 0.4.3
Summary: digsandpaper
Home-page: https://github.com/usc-isi-i2/dig-sandpaper
Author: Jason Slepicka
Author-email: jasonslepicka@gmail.com
License: UNKNOWN
Download-URL: https://github.com/usc-isi-i2/dig-sandpaper
Keywords: ir,search
Platform: UNKNOWN
Requires-Dist: elasticsearch (<3.0.0,>=2.0.0)
Requires-Dist: elasticsearch-dsl (<3.0.0,>=2.0.0)
Requires-Dist: requests
Requires-Dist: Flask
Requires-Dist: Flask-API
Requires-Dist: flask-cors
Requires-Dist: jsonpath-rw (>=1.4.0)
Requires-Dist: jsonpath-rw-ext (>=1.0.0)
